fuzzysets/__init__.py
fuzzysets/plot.py
fuzzysets/tfn.py
fuzzysets/utils.py
fuzzysets/sets/__init__.py
fuzzysets/sets/base.py
fuzzysets/sets/continuous.py
fuzzysets/sets/finite.py
fuzzysets-0.0.4.dist-info/LICENSE
fuzzysets-0.0.4.dist-info/METADATA
fuzzysets-0.0.4.dist-info/WHEEL
fuzzysets-0.0.4.dist-info/top_level.txt
fuzzysets-0.0.4.dist-info/RECORD
