Metadata-Version: 2.1
Name: fuzzysets
Version: 0.0.4
Summary: A package for interactive experiments with fuzzy sets
Home-page: https://github.com/StiliyanDr/fuzzy-sets
Author: Stiliyan Dragnev
Author-email: stiliyan_dragnev@yahoo.com
License: MIT License
Project-URL: Bug Tracker, https://github.com/StiliyanDr/fuzzy-sets/issues
Keywords: fuzzy,set,fuzzyset
Classifier: Programming Language :: Python :: 3
Classifier: License :: OSI Approved :: MIT License
Classifier: Operating System :: OS Independent
Requires-Python: >=3.6
License-File: LICENSE
Requires-Dist: matplotlib
Requires-Dist: numpy
